ovos_translate_server/__init__.py
ovos_translate_server/__main__.py
ovos_translate_server/version.py
ovos_translate_server-0.0.2.dist-info/LICENSE.md
ovos_translate_server-0.0.2.dist-info/METADATA
ovos_translate_server-0.0.2.dist-info/WHEEL
ovos_translate_server-0.0.2.dist-info/entry_points.txt
ovos_translate_server-0.0.2.dist-info/top_level.txt
ovos_translate_server-0.0.2.dist-info/zip-safe
ovos_translate_server-0.0.2.dist-info/RECORD
