Metadata-Version: 2.1
Name: ovos-translate-server
Version: 0.0.2
Summary: simple flask server to host OpenVoiceOS translate plugins as a service
Home-page: https://github.com/OpenVoiceOS/ovos-translate-server
Author: JarbasAi
Author-email: jarbasai@mailfence.com
License: Apache-2.0
Keywords: plugin lang detect translate OVOS OpenVoiceOS
Classifier: Development Status :: 3 - Alpha
Classifier: Intended Audience :: Developers
Classifier: Topic :: Text Processing :: Linguistic
Classifier: License :: OSI Approved :: Apache Software License
Classifier: Programming Language :: Python :: 3.6
Classifier: Programming Language :: Python :: 3.7
Classifier: Programming Language :: Python :: 3.8
Classifier: Programming Language :: Python :: 3.9
Classifier: Programming Language :: Python :: 3.10
Classifier: Programming Language :: Python :: 3.11
License-File: LICENSE.md
Requires-Dist: flask
Requires-Dist: ovos-plugin-manager
